ddco_lab/week5/alu/fulladder.v
module fulladder(A,B,Ci,S,Co);
input A,B,Ci;
output S,Co;
wire w1,w2,w3,w4,w5;
xor G1(w1,A,B);
xor G2(S,Ci,w1);
and G3(w2,A,B);
and G4(w3,B,Ci);
and G5(w4,Ci,A);
or G6(w5,w2,w3);
or G7(Co,w5,w4);
endmodule

ddco_lab/week3/rippleCarryAdder/rca.v
module rca(input wire[3:0] a,b,input wire cin,output wire[3:0] sum,output wire cout);
output wire[2:0] c;
fulladder u0(a[0],b[0],cin,sum[0],cin);
fulladder u1(a[1],b[1],c[0],sum[1],c[1]);
fulladder u2(a[2],b[2],c[1],sum[2],c[2]);
fulladder u3(a[3],b[3],c[2],sum[3],cout);
endmodule

ddco_lab/week3/rippleCarryAdder/rca_tb.v
`timescale 1 ns / 100 ps
`define TESTVECS 10
module tb;
reg clk, reset;
reg [3:0] i0, i1;
reg cin;
wire [3:0] o; 
wire cout;
reg [8:0] test_vecs [0:(`TESTVECS-1)];
integer i;
initial begin 
$dumpfile("rca_test.vcd");
$dumpvars(0,tb); 
end
initial begin
reset = 1'b1; #12.5 reset = 1'b0; end
initial clk = 1'b0; always #5 clk =~ clk;
initial begin
test_vecs[0] = 9'b000000000;
test_vecs[1] = 9'b000000001;
test_vecs[2] = 9'b000100010;
test_vecs[3] = 9'b000100011;
test_vecs[4] = 9'b001000100;
test_vecs[5] = 9'b101010110;
test_vecs[6] = 9'b101010111;
test_vecs[7] = 9'b110011010;
test_vecs[8] = 9'b111111100;
test_vecs[9] = 9'b111111101;
end
initial {i0, i1, cin, i} = 0;
rca u0 (i0, i1, cin, o, cout);
initial begin
#6 for(i=0;i<`TESTVECS;i=i+1)
	begin #10 {i0, i1, cin}=test_vecs[i]; end
#100 $finish;
end
always@(i0 or i1 or cin)
$monitor("At time = %t, i0=%b, i1=%b,cin=%b,Sum = %b,Carry %b", $time,i0,i1,cin,o,cout);
endmodule

ddco_lab/week3/rippleCarryAdder/rca_test.vcd
$date
	Thu Sep 23 18:57:20 2021
$end
$version
	Icarus Verilog
$end
$timescale
	100ps
$end
$scope module tb $end
$var wire 4 ! o [3:0] $end
$var wire 1 " cout $end
$var reg 1 # cin $end
$var reg 1 $ clk $end
$var reg 4 % i0 [3:0] $end
$var reg 4 & i1 [3:0] $end
$var reg 1 ' reset $end
$var integer 32 ( i [31:0] $end
$scope module u0 $end
$var wire 4 ) a [3:0] $end
$var wire 4 * b [3:0] $end
$var wire 1 + cin $end
$var wire 4 , sum [3:0] $end
$var wire 1 " cout $end
$var wire 3 - c [2:0] $end
$scope module u0 $end
$var wire 1 . A $end
$var wire 1 / B $end
$var wire 1 + Ci $end
$var wire 1 + Co $end
$var wire 1 0 S $end
$var wire 1 1 w1 $end
$var wire 1 2 w2 $end
$var wire 1 3 w3 $end
$var wire 1 4 w4 $end
$var wire 1 5 w5 $end
$upscope $end
$scope module u1 $end
$var wire 1 6 A $end
$var wire 1 7 B $end
$var wire 1 8 Ci $end
$var wire 1 9 Co $end
$var wire 1 : S $end
$var wire 1 ; w1 $end
$var wire 1 < w2 $end
$var wire 1 = w3 $end
$var wire 1 > w4 $end
$var wire 1 ? w5 $end
$upscope $end
$scope module u2 $end
$var wire 1 @ A $end
$var wire 1 A B $end
$var wire 1 B Ci $end
$var wire 1 C Co $end
$var wire 1 D S $end
$var wire 1 E w1 $end
$var wire 1 F w2 $end
$var wire 1 G w3 $end
$var wire 1 H w4 $end
$var wire 1 I w5 $end
$upscope $end
$scope module u3 $end
$var wire 1 J A $end
$var wire 1 K B $end
$var wire 1 L Ci $end
$var wire 1 " Co $end
$var wire 1 M S $end
$var wire 1 N w1 $end
$var wire 1 O w2 $end
$var wire 1 P w3 $end
$var wire 1 Q w4 $end
$var wire 1 R w5 $end
$upscope $end
$upscope $end
$upscope $end
$enddefinitions $end
#0
$dumpvars
0R
0Q
0P
0O
0N
0M
0L
0K
0J
0I
0H
0G
0F
0E
0D
0C
0B
0A
0@
0?
0>
0=
0<
0;
x:
09
z8
07
06
05
04
03
02
01
00
0/
0.
b0z -
b0x0 ,
0+
b0 *
b0 )
b0 (
1'
b0 &
b0 %
0$
0#
0"
b0x0 !
$end
#50
1$
#100
0$
#125
0'
#150
1$
#160
b1 (
#200
0$
#250
1$
#260
b0xx !
b0xx ,
x0
b10 (
x+
1#
#300
0$
#350
1$
#360
x3
x4
15
12
1.
1/
b0xx !
b0xx ,
x0
b11 (
b1 %
b1 )
b1 &
b1 *
x+
0#
#400
0$
#450
1$
#460
b0x1 !
b0x1 ,
10
13
14
b100 (
1+
1#
#500
0$
#550
1$
#560
1D
1B
b1z -
19
05
1?
x>
02
1<
x=
0.
16
0/
17
b1x0 !
b1x0 ,
00
03
04
b101 (
b10 %
b10 )
b10 &
b10 *
0+
0#
#600
0$
#650
1$
#660
1"
b1x1 !
b1x1 ,
10
1R
11
1O
1J
1/
1K
b110 (
b1010 %
b1010 )
b1011 &
b1011 *
#700
0$
#750
1$
#760
x5
b1xx !
b1xx ,
x0
x3
b111 (
x+
1#
#800
0$
#850
1$
#860
0D
b10xx !
b10xx ,
1M
1P
1Q
0B
1L
09
b10z -
1C
0?
1I
0>
0H
0<
0=
1F
0G
06
1@
07
1A
b1000 (
b1100 %
b1100 )
b1101 &
b1101 *
0#
#900
0$
#950
1$
#960
b11xx !
b11xx ,
1D
1G
1H
1B
b11z -
19
05
1?
x4
x>
03
1<
x=
1.
16
0/
17
b1001 (
b1111 %
b1111 )
b1110 &
b1110 *
#1000
0$
#1050
1$
#1060
b1010 (
1#
